ra_interp/__init__.py
ra_interp/interpolation.py
ra_interp-0.0.4.dist-info/LICENSE
ra_interp-0.0.4.dist-info/METADATA
ra_interp-0.0.4.dist-info/WHEEL
ra_interp-0.0.4.dist-info/top_level.txt
ra_interp-0.0.4.dist-info/RECORD
